[
  {
    "ContainingType": "KairosAPI.Controllers.ActividadesController",
    "Method": "PostActividad",
    "RelativePath": "api/Actividades",
    "HttpMethod": "POST",
    "IsController": true,
    "Order": 0,
    "Parameters": [
      {
        "Name": "actividad",
        "Type": "KairosAPI.Models.Actividades",
        "IsRequired": true
      }
    ],
    "ReturnTypes": [
      {
        "Type": "KairosAPI.Models.Actividades",
        "MediaTypes": [
          "text/plain",
          "application/json",
          "text/json"
        ],
        "StatusCode": 200
      }
    ]
  },
  {
    "ContainingType": "KairosAPI.Controllers.ActividadesController",
    "Method": "GetByUsuario",
    "RelativePath": "api/Actividades/{idUsuario}",
    "HttpMethod": "GET",
    "IsController": true,
    "Order": 0,
    "Parameters": [
      {
        "Name": "idUsuario",
        "Type": "System.Int32",
        "IsRequired": true
      }
    ],
    "ReturnTypes": [
      {
        "Type": "System.Collections.Generic.IEnumerable\u00601[[KairosAPI.Models.Actividades, KairosAPI, Version=1.0.0.0, Culture=neutral, PublicKeyToken=null]]",
        "MediaTypes": [
          "text/plain",
          "application/json",
          "text/json"
        ],
        "StatusCode": 200
      }
    ]
  },
  {
    "ContainingType": "KairosAPI.Controllers.AuthController",
    "Method": "Login",
    "RelativePath": "api/Auth/login",
    "HttpMethod": "POST",
    "IsController": true,
    "Order": 0,
    "Parameters": [
      {
        "Name": "request",
        "Type": "KairosAPI.Controllers.LoginRequest",
        "IsRequired": true
      }
    ],
    "ReturnTypes": []
  },
  {
    "ContainingType": "KairosAPI.Controllers.AuthController",
    "Method": "Register",
    "RelativePath": "api/Auth/register",
    "HttpMethod": "POST",
    "IsController": true,
    "Order": 0,
    "Parameters": [
      {
        "Name": "rawUser",
        "Type": "System.Text.Json.JsonElement",
        "IsRequired": true
      }
    ],
    "ReturnTypes": []
  },
  {
    "ContainingType": "KairosAPI.Controllers.CategoriasController",
    "Method": "GetCategorias",
    "RelativePath": "api/Categorias",
    "HttpMethod": "GET",
    "IsController": true,
    "Order": 0,
    "Parameters": [],
    "ReturnTypes": [
      {
        "Type": "System.Collections.Generic.IEnumerable\u00601[[KairosAPI.Models.Categoria, KairosAPI, Version=1.0.0.0, Culture=neutral, PublicKeyToken=null]]",
        "MediaTypes": [
          "text/plain",
          "application/json",
          "text/json"
        ],
        "StatusCode": 200
      }
    ]
  },
  {
    "ContainingType": "KairosAPI.Controllers.CategoriasController",
    "Method": "PostCategoria",
    "RelativePath": "api/Categorias",
    "HttpMethod": "POST",
    "IsController": true,
    "Order": 0,
    "Parameters": [
      {
        "Name": "categoria",
        "Type": "KairosAPI.Models.Categoria",
        "IsRequired": true
      }
    ],
    "ReturnTypes": [
      {
        "Type": "KairosAPI.Models.Categoria",
        "MediaTypes": [
          "text/plain",
          "application/json",
          "text/json"
        ],
        "StatusCode": 200
      }
    ]
  },
  {
    "ContainingType": "KairosAPI.Controllers.CategoriasController",
    "Method": "GetCategoria",
    "RelativePath": "api/Categorias/{id}",
    "HttpMethod": "GET",
    "IsController": true,
    "Order": 0,
    "Parameters": [
      {
        "Name": "id",
        "Type": "System.Int32",
        "IsRequired": true
      }
    ],
    "ReturnTypes": [
      {
        "Type": "KairosAPI.Models.Categoria",
        "MediaTypes": [
          "text/plain",
          "application/json",
          "text/json"
        ],
        "StatusCode": 200
      }
    ]
  },
  {
    "ContainingType": "KairosAPI.Controllers.CategoriasController",
    "Method": "PutCategoria",
    "RelativePath": "api/Categorias/{id}",
    "HttpMethod": "PUT",
    "IsController": true,
    "Order": 0,
    "Parameters": [
      {
        "Name": "id",
        "Type": "System.Int32",
        "IsRequired": true
      },
      {
        "Name": "categoria",
        "Type": "KairosAPI.Models.Categoria",
        "IsRequired": true
      }
    ],
    "ReturnTypes": []
  },
  {
    "ContainingType": "KairosAPI.Controllers.CategoriasController",
    "Method": "DeleteCategoria",
    "RelativePath": "api/Categorias/{id}",
    "HttpMethod": "DELETE",
    "IsController": true,
    "Order": 0,
    "Parameters": [
      {
        "Name": "id",
        "Type": "System.Int32",
        "IsRequired": true
      }
    ],
    "ReturnTypes": []
  },
  {
    "ContainingType": "KairosAPI.Controllers.LugaresController",
    "Method": "GetLugares",
    "RelativePath": "api/Lugares",
    "HttpMethod": "GET",
    "IsController": true,
    "Order": 0,
    "Parameters": [],
    "ReturnTypes": [
      {
        "Type": "System.Collections.Generic.IEnumerable\u00601[[KairosAPI.Models.Lugare, KairosAPI, Version=1.0.0.0, Culture=neutral, PublicKeyToken=null]]",
        "MediaTypes": [
          "text/plain",
          "application/json",
          "text/json"
        ],
        "StatusCode": 200
      }
    ]
  },
  {
    "ContainingType": "KairosAPI.Controllers.LugaresController",
    "Method": "PostLugar",
    "RelativePath": "api/Lugares",
    "HttpMethod": "POST",
    "IsController": true,
    "Order": 0,
    "Parameters": [
      {
        "Name": "lugar",
        "Type": "KairosAPI.Models.Lugare",
        "IsRequired": true
      }
    ],
    "ReturnTypes": [
      {
        "Type": "KairosAPI.Models.Lugare",
        "MediaTypes": [
          "text/plain",
          "application/json",
          "text/json"
        ],
        "StatusCode": 200
      }
    ]
  },
  {
    "ContainingType": "KairosAPI.Controllers.LugaresController",
    "Method": "GetLugar",
    "RelativePath": "api/Lugares/{id}",
    "HttpMethod": "GET",
    "IsController": true,
    "Order": 0,
    "Parameters": [
      {
        "Name": "id",
        "Type": "System.Int32",
        "IsRequired": true
      }
    ],
    "ReturnTypes": [
      {
        "Type": "KairosAPI.Models.Lugare",
        "MediaTypes": [
          "text/plain",
          "application/json",
          "text/json"
        ],
        "StatusCode": 200
      }
    ]
  },
  {
    "ContainingType": "KairosAPI.Controllers.LugaresController",
    "Method": "PutLugar",
    "RelativePath": "api/Lugares/{id}",
    "HttpMethod": "PUT",
    "IsController": true,
    "Order": 0,
    "Parameters": [
      {
        "Name": "id",
        "Type": "System.Int32",
        "IsRequired": true
      },
      {
        "Name": "lugar",
        "Type": "KairosAPI.Models.Lugare",
        "IsRequired": true
      }
    ],
    "ReturnTypes": []
  },
  {
    "ContainingType": "KairosAPI.Controllers.LugaresController",
    "Method": "DeleteLugar",
    "RelativePath": "api/Lugares/{id}",
    "HttpMethod": "DELETE",
    "IsController": true,
    "Order": 0,
    "Parameters": [
      {
        "Name": "id",
        "Type": "System.Int32",
        "IsRequired": true
      }
    ],
    "ReturnTypes": []
  },
  {
    "ContainingType": "KairosAPI.Controllers.NotificacionesController",
    "Method": "PostNotificacion",
    "RelativePath": "api/Notificaciones",
    "HttpMethod": "POST",
    "IsController": true,
    "Order": 0,
    "Parameters": [
      {
        "Name": "notificacion",
        "Type": "KairosAPI.Models.Notificacione",
        "IsRequired": true
      }
    ],
    "ReturnTypes": [
      {
        "Type": "KairosAPI.Models.Notificacione",
        "MediaTypes": [
          "text/plain",
          "application/json",
          "text/json"
        ],
        "StatusCode": 200
      }
    ]
  },
  {
    "ContainingType": "KairosAPI.Controllers.NotificacionesController",
    "Method": "DeleteNotificacion",
    "RelativePath": "api/Notificaciones/{id}",
    "HttpMethod": "DELETE",
    "IsController": true,
    "Order": 0,
    "Parameters": [
      {
        "Name": "id",
        "Type": "System.Int32",
        "IsRequired": true
      }
    ],
    "ReturnTypes": []
  },
  {
    "ContainingType": "KairosAPI.Controllers.NotificacionesController",
    "Method": "GetNotificacionesUsuario",
    "RelativePath": "api/Notificaciones/{idUsuario}",
    "HttpMethod": "GET",
    "IsController": true,
    "Order": 0,
    "Parameters": [
      {
        "Name": "idUsuario",
        "Type": "System.Int32",
        "IsRequired": true
      }
    ],
    "ReturnTypes": [
      {
        "Type": "System.Collections.Generic.IEnumerable\u00601[[KairosAPI.Models.Notificacione, KairosAPI, Version=1.0.0.0, Culture=neutral, PublicKeyToken=null]]",
        "MediaTypes": [
          "text/plain",
          "application/json",
          "text/json"
        ],
        "StatusCode": 200
      }
    ]
  },
  {
    "ContainingType": "KairosAPI.Controllers.PromocionesController",
    "Method": "GetPromociones",
    "RelativePath": "api/Promociones",
    "HttpMethod": "GET",
    "IsController": true,
    "Order": 0,
    "Parameters": [],
    "ReturnTypes": [
      {
        "Type": "System.Collections.Generic.IEnumerable\u00601[[KairosAPI.Models.Promocione, KairosAPI, Version=1.0.0.0, Culture=neutral, PublicKeyToken=null]]",
        "MediaTypes": [
          "text/plain",
          "application/json",
          "text/json"
        ],
        "StatusCode": 200
      }
    ]
  },
  {
    "ContainingType": "KairosAPI.Controllers.PromocionesController",
    "Method": "PostPromocion",
    "RelativePath": "api/Promociones",
    "HttpMethod": "POST",
    "IsController": true,
    "Order": 0,
    "Parameters": [
      {
        "Name": "promocion",
        "Type": "KairosAPI.Models.Promocione",
        "IsRequired": true
      }
    ],
    "ReturnTypes": [
      {
        "Type": "KairosAPI.Models.Promocione",
        "MediaTypes": [
          "text/plain",
          "application/json",
          "text/json"
        ],
        "StatusCode": 200
      }
    ]
  },
  {
    "ContainingType": "KairosAPI.Controllers.PromocionesController",
    "Method": "GetPromocion",
    "RelativePath": "api/Promociones/{id}",
    "HttpMethod": "GET",
    "IsController": true,
    "Order": 0,
    "Parameters": [
      {
        "Name": "id",
        "Type": "System.Int32",
        "IsRequired": true
      }
    ],
    "ReturnTypes": [
      {
        "Type": "KairosAPI.Models.Promocione",
        "MediaTypes": [
          "text/plain",
          "application/json",
          "text/json"
        ],
        "StatusCode": 200
      }
    ]
  },
  {
    "ContainingType": "KairosAPI.Controllers.PromocionesController",
    "Method": "PutPromocion",
    "RelativePath": "api/Promociones/{id}",
    "HttpMethod": "PUT",
    "IsController": true,
    "Order": 0,
    "Parameters": [
      {
        "Name": "id",
        "Type": "System.Int32",
        "IsRequired": true
      },
      {
        "Name": "promocion",
        "Type": "KairosAPI.Models.Promocione",
        "IsRequired": true
      }
    ],
    "ReturnTypes": []
  },
  {
    "ContainingType": "KairosAPI.Controllers.PromocionesController",
    "Method": "DeletePromocion",
    "RelativePath": "api/Promociones/{id}",
    "HttpMethod": "DELETE",
    "IsController": true,
    "Order": 0,
    "Parameters": [
      {
        "Name": "id",
        "Type": "System.Int32",
        "IsRequired": true
      }
    ],
    "ReturnTypes": []
  },
  {
    "ContainingType": "KairosAPI.Controllers.RolesController",
    "Method": "GetRoles",
    "RelativePath": "api/Roles",
    "HttpMethod": "GET",
    "IsController": true,
    "Order": 0,
    "Parameters": [],
    "ReturnTypes": [
      {
        "Type": "System.Collections.Generic.IEnumerable\u00601[[KairosAPI.Models.Role, KairosAPI, Version=1.0.0.0, Culture=neutral, PublicKeyToken=null]]",
        "MediaTypes": [
          "text/plain",
          "application/json",
          "text/json"
        ],
        "StatusCode": 200
      }
    ]
  },
  {
    "ContainingType": "KairosAPI.Controllers.RolesController",
    "Method": "PostRol",
    "RelativePath": "api/Roles",
    "HttpMethod": "POST",
    "IsController": true,
    "Order": 0,
    "Parameters": [
      {
        "Name": "rol",
        "Type": "KairosAPI.Models.Role",
        "IsRequired": true
      }
    ],
    "ReturnTypes": [
      {
        "Type": "KairosAPI.Models.Role",
        "MediaTypes": [
          "text/plain",
          "application/json",
          "text/json"
        ],
        "StatusCode": 200
      }
    ]
  },
  {
    "ContainingType": "KairosAPI.Controllers.RolesController",
    "Method": "GetRol",
    "RelativePath": "api/Roles/{id}",
    "HttpMethod": "GET",
    "IsController": true,
    "Order": 0,
    "Parameters": [
      {
        "Name": "id",
        "Type": "System.Int32",
        "IsRequired": true
      }
    ],
    "ReturnTypes": [
      {
        "Type": "KairosAPI.Models.Role",
        "MediaTypes": [
          "text/plain",
          "application/json",
          "text/json"
        ],
        "StatusCode": 200
      }
    ]
  },
  {
    "ContainingType": "KairosAPI.Controllers.RolesController",
    "Method": "PutRol",
    "RelativePath": "api/Roles/{id}",
    "HttpMethod": "PUT",
    "IsController": true,
    "Order": 0,
    "Parameters": [
      {
        "Name": "id",
        "Type": "System.Int32",
        "IsRequired": true
      },
      {
        "Name": "rol",
        "Type": "KairosAPI.Models.Role",
        "IsRequired": true
      }
    ],
    "ReturnTypes": []
  },
  {
    "ContainingType": "KairosAPI.Controllers.RolesController",
    "Method": "DeleteRol",
    "RelativePath": "api/Roles/{id}",
    "HttpMethod": "DELETE",
    "IsController": true,
    "Order": 0,
    "Parameters": [
      {
        "Name": "id",
        "Type": "System.Int32",
        "IsRequired": true
      }
    ],
    "ReturnTypes": []
  },
  {
    "ContainingType": "KairosAPI.Controllers.RutasController",
    "Method": "GetRutas",
    "RelativePath": "api/Rutas",
    "HttpMethod": "GET",
    "IsController": true,
    "Order": 0,
    "Parameters": [],
    "ReturnTypes": [
      {
        "Type": "System.Collections.Generic.IEnumerable\u00601[[KairosAPI.Models.Ruta, KairosAPI, Version=1.0.0.0, Culture=neutral, PublicKeyToken=null]]",
        "MediaTypes": [
          "text/plain",
          "application/json",
          "text/json"
        ],
        "StatusCode": 200
      }
    ]
  },
  {
    "ContainingType": "KairosAPI.Controllers.RutasController",
    "Method": "PostRuta",
    "RelativePath": "api/Rutas",
    "HttpMethod": "POST",
    "IsController": true,
    "Order": 0,
    "Parameters": [
      {
        "Name": "ruta",
        "Type": "KairosAPI.Models.Ruta",
        "IsRequired": true
      }
    ],
    "ReturnTypes": [
      {
        "Type": "KairosAPI.Models.Ruta",
        "MediaTypes": [
          "text/plain",
          "application/json",
          "text/json"
        ],
        "StatusCode": 200
      }
    ]
  },
  {
    "ContainingType": "KairosAPI.Controllers.RutasController",
    "Method": "GetRuta",
    "RelativePath": "api/Rutas/{id}",
    "HttpMethod": "GET",
    "IsController": true,
    "Order": 0,
    "Parameters": [
      {
        "Name": "id",
        "Type": "System.Int32",
        "IsRequired": true
      }
    ],
    "ReturnTypes": [
      {
        "Type": "KairosAPI.Models.Ruta",
        "MediaTypes": [
          "text/plain",
          "application/json",
          "text/json"
        ],
        "StatusCode": 200
      }
    ]
  },
  {
    "ContainingType": "KairosAPI.Controllers.RutasController",
    "Method": "PutRuta",
    "RelativePath": "api/Rutas/{id}",
    "HttpMethod": "PUT",
    "IsController": true,
    "Order": 0,
    "Parameters": [
      {
        "Name": "id",
        "Type": "System.Int32",
        "IsRequired": true
      },
      {
        "Name": "ruta",
        "Type": "KairosAPI.Models.Ruta",
        "IsRequired": true
      }
    ],
    "ReturnTypes": []
  },
  {
    "ContainingType": "KairosAPI.Controllers.RutasController",
    "Method": "DeleteRuta",
    "RelativePath": "api/Rutas/{id}",
    "HttpMethod": "DELETE",
    "IsController": true,
    "Order": 0,
    "Parameters": [
      {
        "Name": "id",
        "Type": "System.Int32",
        "IsRequired": true
      }
    ],
    "ReturnTypes": []
  },
  {
    "ContainingType": "KairosAPI.Controllers.TokensController",
    "Method": "GetTokens",
    "RelativePath": "api/Tokens",
    "HttpMethod": "GET",
    "IsController": true,
    "Order": 0,
    "Parameters": [],
    "ReturnTypes": [
      {
        "Type": "System.Collections.Generic.IEnumerable\u00601[[KairosAPI.Models.Token, KairosAPI, Version=1.0.0.0, Culture=neutral, PublicKeyToken=null]]",
        "MediaTypes": [
          "text/plain",
          "application/json",
          "text/json"
        ],
        "StatusCode": 200
      }
    ]
  },
  {
    "ContainingType": "KairosAPI.Controllers.TokensController",
    "Method": "PostToken",
    "RelativePath": "api/Tokens",
    "HttpMethod": "POST",
    "IsController": true,
    "Order": 0,
    "Parameters": [
      {
        "Name": "token",
        "Type": "KairosAPI.Models.Token",
        "IsRequired": true
      }
    ],
    "ReturnTypes": [
      {
        "Type": "KairosAPI.Models.Token",
        "MediaTypes": [
          "text/plain",
          "application/json",
          "text/json"
        ],
        "StatusCode": 200
      }
    ]
  },
  {
    "ContainingType": "KairosAPI.Controllers.TokensController",
    "Method": "GetToken",
    "RelativePath": "api/Tokens/{id}",
    "HttpMethod": "GET",
    "IsController": true,
    "Order": 0,
    "Parameters": [
      {
        "Name": "id",
        "Type": "System.Int32",
        "IsRequired": true
      }
    ],
    "ReturnTypes": [
      {
        "Type": "KairosAPI.Models.Token",
        "MediaTypes": [
          "text/plain",
          "application/json",
          "text/json"
        ],
        "StatusCode": 200
      }
    ]
  },
  {
    "ContainingType": "KairosAPI.Controllers.TokensController",
    "Method": "PutToken",
    "RelativePath": "api/Tokens/{id}",
    "HttpMethod": "PUT",
    "IsController": true,
    "Order": 0,
    "Parameters": [
      {
        "Name": "id",
        "Type": "System.Int32",
        "IsRequired": true
      },
      {
        "Name": "token",
        "Type": "KairosAPI.Models.Token",
        "IsRequired": true
      }
    ],
    "ReturnTypes": []
  },
  {
    "ContainingType": "KairosAPI.Controllers.TokensController",
    "Method": "DeleteToken",
    "RelativePath": "api/Tokens/{id}",
    "HttpMethod": "DELETE",
    "IsController": true,
    "Order": 0,
    "Parameters": [
      {
        "Name": "id",
        "Type": "System.Int32",
        "IsRequired": true
      }
    ],
    "ReturnTypes": []
  },
  {
    "ContainingType": "KairosAPI.Controllers.TokensController",
    "Method": "GetTokensByUsuario",
    "RelativePath": "api/Tokens/usuario/{idUsuario}",
    "HttpMethod": "GET",
    "IsController": true,
    "Order": 0,
    "Parameters": [
      {
        "Name": "idUsuario",
        "Type": "System.Int32",
        "IsRequired": true
      }
    ],
    "ReturnTypes": [
      {
        "Type": "System.Collections.Generic.IEnumerable\u00601[[KairosAPI.Models.Token, KairosAPI, Version=1.0.0.0, Culture=neutral, PublicKeyToken=null]]",
        "MediaTypes": [
          "text/plain",
          "application/json",
          "text/json"
        ],
        "StatusCode": 200
      }
    ]
  },
  {
    "ContainingType": "KairosAPI.Controllers.UsoDigitalController",
    "Method": "PostUsoDigital",
    "RelativePath": "api/UsoDigital",
    "HttpMethod": "POST",
    "IsController": true,
    "Order": 0,
    "Parameters": [
      {
        "Name": "usoDigital",
        "Type": "KairosAPI.Models.UsoDigital",
        "IsRequired": true
      }
    ],
    "ReturnTypes": [
      {
        "Type": "KairosAPI.Models.UsoDigital",
        "MediaTypes": [
          "text/plain",
          "application/json",
          "text/json"
        ],
        "StatusCode": 200
      }
    ]
  },
  {
    "ContainingType": "KairosAPI.Controllers.UsoDigitalController",
    "Method": "GetByUsuario",
    "RelativePath": "api/UsoDigital/{idUsuario}",
    "HttpMethod": "GET",
    "IsController": true,
    "Order": 0,
    "Parameters": [
      {
        "Name": "idUsuario",
        "Type": "System.Int32",
        "IsRequired": true
      }
    ],
    "ReturnTypes": [
      {
        "Type": "System.Collections.Generic.IEnumerable\u00601[[KairosAPI.Models.UsoDigital, KairosAPI, Version=1.0.0.0, Culture=neutral, PublicKeyToken=null]]",
        "MediaTypes": [
          "text/plain",
          "application/json",
          "text/json"
        ],
        "StatusCode": 200
      }
    ]
  },
  {
    "ContainingType": "KairosAPI.Controllers.UsuariosController",
    "Method": "GetUsuarios",
    "RelativePath": "api/Usuarios",
    "HttpMethod": "GET",
    "IsController": true,
    "Order": 0,
    "Parameters": [],
    "ReturnTypes": [
      {
        "Type": "System.Collections.Generic.IEnumerable\u00601[[KairosAPI.Models.Usuario, KairosAPI, Version=1.0.0.0, Culture=neutral, PublicKeyToken=null]]",
        "MediaTypes": [
          "text/plain",
          "application/json",
          "text/json"
        ],
        "StatusCode": 200
      }
    ]
  },
  {
    "ContainingType": "KairosAPI.Controllers.UsuariosController",
    "Method": "PostUsuario",
    "RelativePath": "api/Usuarios",
    "HttpMethod": "POST",
    "IsController": true,
    "Order": 0,
    "Parameters": [
      {
        "Name": "usuario",
        "Type": "KairosAPI.Models.Usuario",
        "IsRequired": true
      }
    ],
    "ReturnTypes": [
      {
        "Type": "KairosAPI.Models.Usuario",
        "MediaTypes": [
          "text/plain",
          "application/json",
          "text/json"
        ],
        "StatusCode": 200
      }
    ]
  },
  {
    "ContainingType": "KairosAPI.Controllers.UsuariosController",
    "Method": "GetUsuario",
    "RelativePath": "api/Usuarios/{id}",
    "HttpMethod": "GET",
    "IsController": true,
    "Order": 0,
    "Parameters": [
      {
        "Name": "id",
        "Type": "System.Int32",
        "IsRequired": true
      }
    ],
    "ReturnTypes": [
      {
        "Type": "KairosAPI.Models.Usuario",
        "MediaTypes": [
          "text/plain",
          "application/json",
          "text/json"
        ],
        "StatusCode": 200
      }
    ]
  },
  {
    "ContainingType": "KairosAPI.Controllers.UsuariosController",
    "Method": "PutUsuario",
    "RelativePath": "api/Usuarios/{id}",
    "HttpMethod": "PUT",
    "IsController": true,
    "Order": 0,
    "Parameters": [
      {
        "Name": "id",
        "Type": "System.Int32",
        "IsRequired": true
      },
      {
        "Name": "usuario",
        "Type": "KairosAPI.Models.Usuario",
        "IsRequired": true
      }
    ],
    "ReturnTypes": []
  },
  {
    "ContainingType": "KairosAPI.Controllers.UsuariosController",
    "Method": "DeleteUsuario",
    "RelativePath": "api/Usuarios/{id}",
    "HttpMethod": "DELETE",
    "IsController": true,
    "Order": 0,
    "Parameters": [
      {
        "Name": "id",
        "Type": "System.Int32",
        "IsRequired": true
      }
    ],
    "ReturnTypes": []
  },
  {
    "ContainingType": "KairosAPI.Controllers.UsuariosController",
    "Method": "CambiarEstatus",
    "RelativePath": "api/Usuarios/{id}/estatus",
    "HttpMethod": "PATCH",
    "IsController": true,
    "Order": 0,
    "Parameters": [
      {
        "Name": "id",
        "Type": "System.Int32",
        "IsRequired": true
      }
    ],
    "ReturnTypes": []
  }
]